discordub/__init__.py
discordub-0.1.11.dist-info/LICENSE
discordub-0.1.11.dist-info/METADATA
discordub-0.1.11.dist-info/WHEEL
discordub-0.1.11.dist-info/top_level.txt
discordub-0.1.11.dist-info/RECORD
