Metadata-Version: 2.1
Name: discordub
Version: 0.1.11
Summary: A python package that controls the discord user. Not to be confused with discord bots.
Author-email: qloha <sirfigaloha@gmail.com>
Project-URL: Homepage, https://github.com/qloha/dub
Project-URL: Issues, https://github.com/qloha/dub/issues
Classifier: Programming Language :: Python :: 3
Classifier: License :: OSI Approved :: MIT License
Classifier: Operating System :: OS Independent
Requires-Python: >=3.8
License-File: LICENSE
